render_python-2.4.2.dist-info/licenses/LICENSE
renderapi/__init__.py
renderapi/_version.py
renderapi/channel.py
renderapi/coordinate.py
renderapi/errors.py
renderapi/image.py
renderapi/image_pyramid.py
renderapi/layout.py
renderapi/pointmatch.py
renderapi/render.py
renderapi/resolvedtiles.py
renderapi/stack.py
renderapi/tilespec.py
renderapi/utils.py
renderapi/client/__init__.py
renderapi/client/client.py
renderapi/client/client_calls.py
renderapi/client/params.py
renderapi/client/utils.py
renderapi/external/__init__.py
renderapi/external/processpools/__init__.py
renderapi/external/processpools/pool_pathos.py
renderapi/external/processpools/stdlib_pool.py
renderapi/transform/__init__.py
renderapi/transform/transform.py
renderapi/transform/utils.py
renderapi/transform/leaf/__init__.py
renderapi/transform/leaf/affine_models.py
renderapi/transform/leaf/common.py
renderapi/transform/leaf/polynomial_models.py
renderapi/transform/leaf/thin_plate_spline.py
renderapi/transform/leaf/transform.py
renderapi/transform/leaf/utils.py
render_python-2.4.2.dist-info/METADATA
render_python-2.4.2.dist-info/WHEEL
render_python-2.4.2.dist-info/top_level.txt
render_python-2.4.2.dist-info/RECORD
