Metadata-Version: 2.4
Name: render-python
Version: 2.4.2
Summary: python API client to interact with render databases (see https://github.com/saalfeldlab/render)
Author: Forrest Collman, Russel Torres, Eric Perlman, Sharmi Seshamani
Maintainer: Russel Torres
License: BSD 2-Clause License
Project-URL: Repository, https://github.com/AllenInstitute/render-python.git
Requires-Python: <3.14,>3.8
License-File: LICENSE
Requires-Dist: requests
Requires-Dist: scipy
Requires-Dist: numpy
Requires-Dist: pillow
Requires-Dist: sphinxcontrib-napoleon
Requires-Dist: decorator
Requires-Dist: six
Provides-Extra: test
Requires-Dist: coverage>=4.1; extra == "test"
Requires-Dist: mock>=2.0.0; extra == "test"
Requires-Dist: pep8>=1.7.0; extra == "test"
Requires-Dist: pytest; extra == "test"
Requires-Dist: pytest-cov>=2.2.1; extra == "test"
Requires-Dist: pytest-pep8>=1.0.6; extra == "test"
Requires-Dist: pytest-xdist>=1.14; extra == "test"
Requires-Dist: flake8>=3.0.4; extra == "test"
Requires-Dist: pylint>=1.5.4; extra == "test"
Requires-Dist: jinja2; extra == "test"
Requires-Dist: ujson; extra == "test"
Provides-Extra: pypi-build
Requires-Dist: build; extra == "pypi-build"
Requires-Dist: twine; extra == "pypi-build"
Dynamic: license-file
